LICENSE
README.md
setup.py
servo_config_reader/JsonParser.py
servo_config_reader/__init__.py
servo_config_reader.egg-info/PKG-INFO
servo_config_reader.egg-info/SOURCES.txt
servo_config_reader.egg-info/dependency_links.txt
servo_config_reader.egg-info/top_level.txt