Metadata-Version: 2.1
Name: servo-config-reader
Version: 0.0.1
Summary: Read position range config
Home-page: https://github.com/Adam-Software/Servo-config-reader
Author: vertigra
Author-email: a@nesterof.com
License: MIT
Platform: UNKNOWN
Classifier: Development Status :: 3 - Alpha
Classifier: License :: OSI Approved :: MIT License
Classifier: Operating System :: POSIX :: Linux
Classifier: Programming Language :: Python :: 3.7
Classifier: Programming Language :: Python :: 3.8
Classifier: Programming Language :: Python :: 3.9
License-File: LICENSE
